Metadata-Version: 1.1
Name: uwosh.snippets
Version: 2.0.4
Summary: Adds reusable dynamically-rendered rich-text snippets
Home-page: https://github.com/collective/uwosh.snippets
Author: Sam Schwartz
Author-email: sam.schwartz@wildcardcorp.com
License: gpl
Keywords: snippet,dynamic,reusable,fragment
Platform: UNKNOWN
Classifier: Environment :: Web Environment
Classifier: Framework :: Plone
Classifier: Framework :: Plone :: 5.0
Classifier: Operating System :: OS Independent
Classifier: Programming Language :: Python
Classifier: Programming Language :: Python :: 2.7
Classifier: Topic :: Software Development :: Libraries :: Python Modules
